updrage_packages/__init__.py
updrage_packages/updrage_packages.py
updrage_packages-1.0.0.dist-info/METADATA
updrage_packages-1.0.0.dist-info/WHEEL
updrage_packages-1.0.0.dist-info/top_level.txt
updrage_packages-1.0.0.dist-info/RECORD
