Metadata-Version: 2.1
Name: updrage-packages
Version: 1.0.0
Summary: UNKNOWN
Home-page: UNKNOWN
License: UNKNOWN
Platform: UNKNOWN
Requires-Dist: pip
